{
  "openapi": "3.0.1",
  "info": {
    "title": "School API",
    "version": "v1"
  },
  "paths": {
    "/api/v1/CourseManages": {
      "get": {
        "tags": [
          "CourseManagement"
        ],
        "responses": {
          "200": {
            "description": "Success"
          }
        }
      },
      "post": {
        "tags": [
          "CourseManagement"
        ],
        "operationId": "CourseManageByID",
        "requestBody": {
          "content": {
            "application/json": {
              "schema": {
                "$ref": "#/components/schemas/CourseManageForCreationDto"
              }
            },
            "text/json": {
              "schema": {
                "$ref": "#/components/schemas/CourseManageForCreationDto"
              }
            },
            "application/*+json": {
              "schema": {
                "$ref": "#/components/schemas/CourseManageForCreationDto"
              }
            }
          }
        },
        "responses": {
          "200": {
            "description": "Success"
          }
        }
      }
    },
    "/api/v1/CourseManages/{id}": {
      "get": {
        "tags": [
          "CourseManagement"
        ],
        "parameters": [
          {
            "name": "id",
            "in": "path",
            "required": true,
            "schema": {
              "type": "string",
              "format": "uuid"
            }
          }
        ],
        "responses": {
          "200": {
            "description": "Success"
          }
        }
      },
      "put": {
        "tags": [
          "CourseManagement"
        ],
        "parameters": [
          {
            "name": "id",
            "in": "path",
            "required": true,
            "schema": {
              "type": "string",
              "format": "uuid"
            }
          }
        ],
        "requestBody": {
          "content": {
            "application/json": {
              "schema": {
                "$ref": "#/components/schemas/CourseManageForUpdateDto"
              }
            },
            "text/json": {
              "schema": {
                "$ref": "#/components/schemas/CourseManageForUpdateDto"
              }
            },
            "application/*+json": {
              "schema": {
                "$ref": "#/components/schemas/CourseManageForUpdateDto"
              }
            }
          }
        },
        "responses": {
          "200": {
            "description": "Success"
          }
        }
      },
      "delete": {
        "tags": [
          "CourseManagement"
        ],
        "parameters": [
          {
            "name": "id",
            "in": "path",
            "required": true,
            "schema": {
              "type": "string",
              "format": "uuid"
            }
          }
        ],
        "responses": {
          "200": {
            "description": "Success"
          }
        }
      }
    },
    "/api/v1/Courses": {
      "get": {
        "tags": [
          "Courses"
        ],
        "responses": {
          "200": {
            "description": "Success"
          }
        }
      },
      "post": {
        "tags": [
          "Courses"
        ],
        "operationId": "CourseByID",
        "requestBody": {
          "content": {
            "application/json": {
              "schema": {
                "$ref": "#/components/schemas/CourseForCreationDto"
              }
            },
            "text/json": {
              "schema": {
                "$ref": "#/components/schemas/CourseForCreationDto"
              }
            },
            "application/*+json": {
              "schema": {
                "$ref": "#/components/schemas/CourseForCreationDto"
              }
            }
          }
        },
        "responses": {
          "200": {
            "description": "Success"
          }
        }
      }
    },
    "/api/v1/Courses/{id}": {
      "get": {
        "tags": [
          "Courses"
        ],
        "parameters": [
          {
            "name": "id",
            "in": "path",
            "required": true,
            "schema": {
              "type": "string",
              "format": "uuid"
            }
          }
        ],
        "responses": {
          "200": {
            "description": "Success"
          }
        }
      },
      "put": {
        "tags": [
          "Courses"
        ],
        "parameters": [
          {
            "name": "id",
            "in": "path",
            "required": true,
            "schema": {
              "type": "string",
              "format": "uuid"
            }
          }
        ],
        "requestBody": {
          "content": {
            "application/json": {
              "schema": {
                "$ref": "#/components/schemas/CourseForUpdateDto"
              }
            },
            "text/json": {
              "schema": {
                "$ref": "#/components/schemas/CourseForUpdateDto"
              }
            },
            "application/*+json": {
              "schema": {
                "$ref": "#/components/schemas/CourseForUpdateDto"
              }
            }
          }
        },
        "responses": {
          "200": {
            "description": "Success"
          }
        }
      },
      "delete": {
        "tags": [
          "Courses"
        ],
        "parameters": [
          {
            "name": "id",
            "in": "path",
            "required": true,
            "schema": {
              "type": "string",
              "format": "uuid"
            }
          }
        ],
        "responses": {
          "200": {
            "description": "Success"
          }
        }
      }
    },
    "/api/v1/SectionAssign": {
      "get": {
        "tags": [
          "SectionAssignments"
        ],
        "responses": {
          "200": {
            "description": "Success"
          }
        }
      },
      "post": {
        "tags": [
          "SectionAssignments"
        ],
        "operationId": "SectionAssignByID",
        "requestBody": {
          "content": {
            "application/json": {
              "schema": {
                "$ref": "#/components/schemas/SectionAssignForCreationDTO"
              }
            },
            "text/json": {
              "schema": {
                "$ref": "#/components/schemas/SectionAssignForCreationDTO"
              }
            },
            "application/*+json": {
              "schema": {
                "$ref": "#/components/schemas/SectionAssignForCreationDTO"
              }
            }
          }
        },
        "responses": {
          "200": {
            "description": "Success"
          }
        }
      }
    },
    "/api/v1/SectionAssign/{id}": {
      "get": {
        "tags": [
          "SectionAssignments"
        ],
        "parameters": [
          {
            "name": "id",
            "in": "path",
            "required": true,
            "schema": {
              "type": "string",
              "format": "uuid"
            }
          }
        ],
        "responses": {
          "200": {
            "description": "Success"
          }
        }
      },
      "put": {
        "tags": [
          "SectionAssignments"
        ],
        "parameters": [
          {
            "name": "id",
            "in": "path",
            "required": true,
            "schema": {
              "type": "string",
              "format": "uuid"
            }
          }
        ],
        "requestBody": {
          "content": {
            "application/json": {
              "schema": {
                "$ref": "#/components/schemas/SectionAssignForUpdateDTO"
              }
            },
            "text/json": {
              "schema": {
                "$ref": "#/components/schemas/SectionAssignForUpdateDTO"
              }
            },
            "application/*+json": {
              "schema": {
                "$ref": "#/components/schemas/SectionAssignForUpdateDTO"
              }
            }
          }
        },
        "responses": {
          "200": {
            "description": "Success"
          }
        }
      },
      "delete": {
        "tags": [
          "SectionAssignments"
        ],
        "parameters": [
          {
            "name": "id",
            "in": "path",
            "required": true,
            "schema": {
              "type": "string",
              "format": "uuid"
            }
          }
        ],
        "responses": {
          "200": {
            "description": "Success"
          }
        }
      }
    },
    "/api/v1/organizations": {
      "get": {
        "tags": [
          "User"
        ],
        "responses": {
          "200": {
            "description": "Success"
          }
        }
      },
      "post": {
        "tags": [
          "User"
        ],
        "operationId": "UserByID",
        "requestBody": {
          "content": {
            "application/json": {
              "schema": {
                "$ref": "#/components/schemas/UserForCreationDto"
              }
            },
            "text/json": {
              "schema": {
                "$ref": "#/components/schemas/UserForCreationDto"
              }
            },
            "application/*+json": {
              "schema": {
                "$ref": "#/components/schemas/UserForCreationDto"
              }
            }
          }
        },
        "responses": {
          "200": {
            "description": "Success"
          }
        }
      }
    },
    "/api/v1/organizations/{id}": {
      "get": {
        "tags": [
          "User"
        ],
        "parameters": [
          {
            "name": "id",
            "in": "path",
            "required": true,
            "schema": {
              "type": "string",
              "format": "uuid"
            }
          }
        ],
        "responses": {
          "200": {
            "description": "Success"
          }
        }
      },
      "put": {
        "tags": [
          "User"
        ],
        "parameters": [
          {
            "name": "id",
            "in": "path",
            "required": true,
            "schema": {
              "type": "string",
              "format": "uuid"
            }
          }
        ],
        "requestBody": {
          "content": {
            "application/json": {
              "schema": {
                "$ref": "#/components/schemas/UserForUpdateDto"
              }
            },
            "text/json": {
              "schema": {
                "$ref": "#/components/schemas/UserForUpdateDto"
              }
            },
            "application/*+json": {
              "schema": {
                "$ref": "#/components/schemas/UserForUpdateDto"
              }
            }
          }
        },
        "responses": {
          "200": {
            "description": "Success"
          }
        }
      },
      "delete": {
        "tags": [
          "User"
        ],
        "parameters": [
          {
            "name": "id",
            "in": "path",
            "required": true,
            "schema": {
              "type": "string",
              "format": "uuid"
            }
          }
        ],
        "responses": {
          "200": {
            "description": "Success"
          }
        }
      }
    },
    "/WeatherForecast": {
      "get": {
        "tags": [
          "WeatherForecast"
        ],
        "responses": {
          "200": {
            "description": "Success",
            "content": {
              "text/plain": {
                "schema": {
                  "type": "array",
                  "items": {
                    "$ref": "#/components/schemas/WeatherForecast"
                  }
                }
              },
              "application/json": {
                "schema": {
                  "type": "array",
                  "items": {
                    "$ref": "#/components/schemas/WeatherForecast"
                  }
                }
              },
              "text/json": {
                "schema": {
                  "type": "array",
                  "items": {
                    "$ref": "#/components/schemas/WeatherForecast"
                  }
                }
              }
            }
          }
        }
      }
    }
  },
  "components": {
    "schemas": {
      "CourseManageForCreationDto": {
        "required": [
          "assigmentID",
          "assignmentTitle",
          "description"
        ],
        "type": "object",
        "properties": {
          "assigmentID": {
            "type": "integer",
            "format": "int32"
          },
          "assignmentTitle": {
            "type": "string"
          },
          "description": {
            "maxLength": 60,
            "minLength": 20,
            "type": "string"
          }
        },
        "additionalProperties": false
      },
      "CourseManageForUpdateDto": {
        "type": "object",
        "properties": {
          "assigmentID": {
            "type": "integer",
            "format": "int32"
          },
          "assignmentTitle": {
            "type": "string",
            "nullable": true
          },
          "description": {
            "type": "string",
            "nullable": true
          }
        },
        "additionalProperties": false
      },
      "CourseForCreationDto": {
        "required": [
          "courseName",
          "createdDate",
          "description",
          "updatedDate"
        ],
        "type": "object",
        "properties": {
          "courseName": {
            "maxLength": 25,
            "minLength": 10,
            "type": "string"
          },
          "description": {
            "maxLength": 50,
            "minLength": 10,
            "type": "string"
          },
          "createdDate": {
            "type": "string",
            "format": "date-time"
          },
          "updatedDate": {
            "type": "string",
            "format": "date-time"
          }
        },
        "additionalProperties": false
      },
      "CourseForUpdateDto": {
        "required": [
          "courseName",
          "createdDate",
          "description",
          "updatedDate"
        ],
        "type": "object",
        "properties": {
          "courseName": {
            "maxLength": 25,
            "minLength": 10,
            "type": "string"
          },
          "description": {
            "maxLength": 50,
            "minLength": 10,
            "type": "string"
          },
          "createdDate": {
            "type": "string",
            "format": "date-time"
          },
          "updatedDate": {
            "type": "string",
            "format": "date-time"
          }
        },
        "additionalProperties": false
      },
      "SectionAssignForCreationDTO": {
        "required": [
          "createdDate",
          "score",
          "submissionText",
          "updatedDate"
        ],
        "type": "object",
        "properties": {
          "submissionText": {
            "maxLength": 60,
            "minLength": 10,
            "type": "string"
          },
          "score": {
            "type": "integer",
            "format": "int32"
          },
          "createdDate": {
            "type": "string",
            "format": "date-time"
          },
          "updatedDate": {
            "type": "string",
            "format": "date-time"
          },
          "usersID": {
            "type": "string",
            "nullable": true
          },
          "assignID": {
            "type": "string",
            "nullable": true
          }
        },
        "additionalProperties": false
      },
      "SectionAssignForUpdateDTO": {
        "required": [
          "createdDate",
          "score",
          "submissionText",
          "updatedDate"
        ],
        "type": "object",
        "properties": {
          "submissionText": {
            "maxLength": 60,
            "minLength": 10,
            "type": "string"
          },
          "score": {
            "type": "integer",
            "format": "int32"
          },
          "createdDate": {
            "type": "string",
            "format": "date-time"
          },
          "updatedDate": {
            "type": "string",
            "format": "date-time"
          },
          "usersID": {
            "type": "string",
            "nullable": true
          },
          "assignID": {
            "type": "string",
            "nullable": true
          }
        },
        "additionalProperties": false
      },
      "UserForCreationDto": {
        "required": [
          "email",
          "status",
          "username"
        ],
        "type": "object",
        "properties": {
          "username": {
            "maxLength": 20,
            "minLength": 10,
            "type": "string"
          },
          "email": {
            "maxLength": 20,
            "minLength": 5,
            "type": "string"
          },
          "status": {
            "type": "string"
          },
          "organizationId": {
            "type": "string",
            "nullable": true
          },
          "courseID": {
            "type": "string",
            "nullable": true
          }
        },
        "additionalProperties": false
      },
      "UserForUpdateDto": {
        "type": "object",
        "properties": {
          "email": {
            "type": "string",
            "nullable": true
          },
          "username": {
            "type": "string",
            "nullable": true
          },
          "status": {
            "type": "string",
            "nullable": true
          }
        },
        "additionalProperties": false
      },
      "WeatherForecast": {
        "type": "object",
        "properties": {
          "date": {
            "type": "string",
            "format": "date-time"
          },
          "temperatureC": {
            "type": "integer",
            "format": "int32"
          },
          "temperatureF": {
            "type": "integer",
            "format": "int32",
            "readOnly": true
          },
          "summary": {
            "type": "string",
            "nullable": true
          }
        },
        "additionalProperties": false
      }
    }
  }
}